libpci-0.2.data/scripts/pci-lookup
libpci-0.2.dist-info/WHEEL
libpci-0.2.dist-info/zip-safe
libpci-0.2.dist-info/DESCRIPTION.rst
libpci-0.2.dist-info/RECORD
libpci-0.2.dist-info/metadata.json
libpci-0.2.dist-info/METADATA
libpci-0.2.dist-info/top_level.txt
libpci/_macros.py
libpci/_native.py
libpci/_types.py
libpci/wrapper.py
libpci/_functions.py
libpci/__init__.py
