Metadata-Version: 2.0
Name: libpci
Version: 0.2
Summary: Pure-Python, high-level bindings to libpci
Home-page: https://github.com/zyga/libpci
Author: Zygmunt Krynicki
Author-email: zygmunt.krunicki@canonical.com
License: LGPLv3
Keywords: libpci binding
Platform: UNKNOWN
Classifier: Development Status :: 3 - Alpha
Classifier: Intended Audience :: Developers
Classifier: Environment :: Console
Classifier: License :: OSI Approved :: GNU Lesser General Public License v3 (LGPLv3)
Classifier: Natural Language :: English
Classifier: Operating System :: POSIX :: Linux
Classifier: Topic :: Software Development
Classifier: Topic :: Software Development :: Libraries
Classifier: Programming Language :: Python :: 3
Classifier: Programming Language :: Python :: 3.4
Classifier: Programming Language :: Python :: Implementation :: CPython
Requires-Dist: guacamole
